{"stat.useItem.minecraft.diamond_hoe":47,"stat.walkOneCm":203154,"achievement.openInventory":1,"stat.pickup.minecraft.carrot_on_a_stick":8,"stat.leaveGame":2,"stat.damageTaken":18223,"stat.useItem.minecraft.golden_pickaxe":3,"stat.useItem.minecraft.lingering_potion":280,"stat.useItem.minecraft.carrot_on_a_stick":98,"stat.flyOneCm":274038,"stat.drop":2,"stat.jump":558,"stat.swimOneCm":311,"stat.playOneMinute":80905,"stat.fallOneCm":332203,"stat.sneakTime":460,"stat.pickup.minecraft.golden_pickaxe":5,"stat.drop.minecraft.diamond_hoe":2,"stat.damageDealt":5090,"stat.crouchOneCm":768,"stat.timeSinceDeath":80905,"stat.sprintOneCm":68257,"achievement.exploreAllBiomes":{"value":0,"progress":["Plains"]}}